Metadata-Version: 2.1
Name: jaffatools
Version: 0.5.0
Summary: Tools for working with JAFFA fusion gene detection
Home-page: https://github.com/WhaleGe/jaffatools
Author: Waidong Huang
Author-email: wdhuang927@gmail.com
License: UNKNOWN
Platform: UNKNOWN
Classifier: Programming Language :: Python :: 3
Classifier: License :: OSI Approved :: MIT License
Classifier: Operating System :: OS Independent
Classifier: Topic :: Scientific/Engineering :: Bio-Informatics
Requires-Python: >=3.6
License-File: LICENSE
